README.md
setup.py
dockering/__init__.py
dockering/config_building.py
dockering/core.py
dockering/exceptions.py
dockering/utils.py
onap_dcae_dockering_fiberhome.egg-info/PKG-INFO
onap_dcae_dockering_fiberhome.egg-info/SOURCES.txt
onap_dcae_dockering_fiberhome.egg-info/dependency_links.txt
onap_dcae_dockering_fiberhome.egg-info/not-zip-safe
onap_dcae_dockering_fiberhome.egg-info/requires.txt
onap_dcae_dockering_fiberhome.egg-info/top_level.txt