Metadata-Version: 1.0
Name: onap-dcae-dockering-fiberhome
Version: 1.4.1
Summary: Library used to manage Docker containers in DCAE, revised by FiberHome
Home-page: UNKNOWN
Author: Minglu Li
Author-email: UNKNOWN
License: Apache 2
Platform: UNKNOWN
